{
  "type": "minecraft:crafting_shaped",
  "category": "misc",
  "pattern": [
    " 1 ",
    "345",
    " 7 "
  ],
  "key": {
    "1": {
      "item": "minecraft:redstone"
    },
    "3": {
      "item": "supreme_mining_dimension:raw_nickel"
    },
    "4": {
      "item": "minecraft:slime_ball"
    },
    "5": {
      "item": "supreme_mining_dimension:raw_nickel"
    },
    "7": {
      "item": "minecraft:poisonous_potato"
    }
  },
  "result": {
    "item": "supreme_mining_dimension:slime_chow",
    "count": 4
  }
}